pytronic/__init__.py
pytronic/bot.py
pytronic/client.py
pytronic/commands/base/command.py
pytronic/commands/createbot.py
pytronic/commands/run.py
pytronic/commands/start.py
pytronic/components/__init__.py
pytronic/components/keyboard.py
pytronic/components/mouse.py
pytronic/components/screen.py
pytronic/computer_interaction.py
pytronic/factory/__init__.py
pytronic/factory/bot_factory.py
pytronic/management/__init__.py
pytronic/management/bot_loader.py
pytronic/management/file_manager.py
pytronic/templates/bot_template.py.jinja
pytronic/templates/settings.py.jinja
pytronic/templates/task_template.py.jinja
pytronic/utils.py
pytronic-0.1.3.dist-info/LICENSE
pytronic-0.1.3.dist-info/METADATA
pytronic-0.1.3.dist-info/WHEEL
pytronic-0.1.3.dist-info/entry_points.txt
pytronic-0.1.3.dist-info/RECORD
