Metadata-Version: 2.1
Name: pytronic
Version: 0.1.3
Summary: 
Author: Samuel Sublate
Author-email: samuelsublate.dev@gmail.com
Requires-Python: >=3.12,<4.0
Classifier: Programming Language :: Python :: 3
Classifier: Programming Language :: Python :: 3.12
Requires-Dist: blue (>=0.9.1,<0.10.0)
Requires-Dist: jinja2 (>=3.1.4,<4.0.0)
Requires-Dist: numpy (>=2.0.0,<3.0.0)
Requires-Dist: opencv-python (>=4.10.0.84,<5.0.0.0)
Requires-Dist: pillow (>=10.4.0,<11.0.0)
Requires-Dist: pyautogui (>=0.9.54,<0.10.0)
Requires-Dist: pydantic (>=2.8.0,<3.0.0)
Requires-Dist: pytesseract (>=0.3.10,<0.4.0)
Requires-Dist: pytest (>=8.2.2,<9.0.0)
Requires-Dist: taskipy (>=1.13.0,<2.0.0)
Requires-Dist: typer (>=0.12.3,<0.13.0)
